close_paving/__init__.py
close_paving/core/__init__.py
close_paving/core/cell.py
close_paving/core/direction.py
close_paving/core/hexagon.py
close_paving/core/hexagonal_grid.py
close_paving/error/__init__.py
close_paving/kernel/__init__.py
close_paving/kernel/gen_kernel.py
close_paving/plot_helper/__init__.py
close_paving/plot_helper/plot_helper.py
close_paving-0.1.dist-info/licenses/LICENSE
close_paving-0.1.dist-info/METADATA
close_paving-0.1.dist-info/WHEEL
close_paving-0.1.dist-info/top_level.txt
close_paving-0.1.dist-info/RECORD
